prm/__init__.py
prm/__main__.py
prm/prm.py
prm-0.1.4.dist-info/entry_points.txt
prm-0.1.4.dist-info/LICENSE
prm-0.1.4.dist-info/WHEEL
prm-0.1.4.dist-info/METADATA
prm-0.1.4.dist-info/RECORD
