Metadata-Version: 2.1
Name: prm
Version: 0.1.4
Summary: pip repository manager
License: MIT
Author: duyixian
Author-email: duyixian1234@qq.com
Requires-Python: >=3.8,<4.0
Classifier: License :: OSI Approved :: MIT License
Classifier: Programming Language :: Python :: 3
Classifier: Programming Language :: Python :: 3.8
Classifier: Programming Language :: Python :: 3.9
Requires-Dist: click (>=7.1.2,<8.0.0)
